odoo/addons/ssi_state_change_history_mixin/README.rst
odoo/addons/ssi_state_change_history_mixin/__init__.py
odoo/addons/ssi_state_change_history_mixin/__manifest__.py
odoo/addons/ssi_state_change_history_mixin/menu.xml
odoo/addons/ssi_state_change_history_mixin/i18n/ssi_state_change_history_mixin.pot
odoo/addons/ssi_state_change_history_mixin/models/__init__.py
odoo/addons/ssi_state_change_history_mixin/models/mixin_state_change_history.py
odoo/addons/ssi_state_change_history_mixin/models/state_change_history.py
odoo/addons/ssi_state_change_history_mixin/security/ir.model.access.csv
odoo/addons/ssi_state_change_history_mixin/static/description/icon.png
odoo/addons/ssi_state_change_history_mixin/templates/mixin_state_change_history_templates.xml
odoo/addons/ssi_state_change_history_mixin/views/state_change_history_views.xml
odoo14_addon_ssi_state_change_history_mixin-14.0.1.2.0.dist-info/METADATA
odoo14_addon_ssi_state_change_history_mixin-14.0.1.2.0.dist-info/WHEEL
odoo14_addon_ssi_state_change_history_mixin-14.0.1.2.0.dist-info/top_level.txt
odoo14_addon_ssi_state_change_history_mixin-14.0.1.2.0.dist-info/RECORD
